__init__.py
kv_image_pipeline/__init__.py
kv_image_pipeline/image_pipeline.py
kv_image_pipeline-0.1.2.dist-info/METADATA
kv_image_pipeline-0.1.2.dist-info/WHEEL
kv_image_pipeline-0.1.2.dist-info/top_level.txt
kv_image_pipeline-0.1.2.dist-info/RECORD
